{
  "$schema": "http://json-schema.org/schema",
  "id": "WdtkWorkspaceSchematicsNgNew",
  "title": "Workspace Ng New Options Schema",
  "type": "object",
  "properties": {
    "name": {
      "description": "The name of the new workspace.",
      "type": "string",
      "format": "html-selector",
      "$default": {
        "$source": "argv",
        "index": 0
      },
      "x-prompt": "What name would you like to use for the workspace?"
    },
    "directory": {
      "description": "The directory name to create the workspace in.",
      "type": "string"
    },

    "commit": {
      "description": "Initial git repository commit information.",
      "oneOf": [
        { "type": "boolean" },
        {
          "type": "object",
          "properties": {
            "name": { "type": "string" },
            "email": { "type": "string", "format": "email" },
            "message": { "type": "string" }
          },
          "required": ["name", "email"]
        }
      ],
      "default": true
    },
    "skipGit": {
      "description": "When true, does not initialize a git repository.",
      "type": "boolean",
      "default": false
    },
    "skipInstall": {
      "description": "When true, does not install dependency packages.",
      "type": "boolean",
      "default": false
    },
    "skipYarn": {
      "description": "When true, does not initialize yarn 2.",
      "type": "boolean",
      "default": false
    }
  },
  "required": ["name"]
}
